fauxdoc/__init__.py
fauxdoc/dtrange.py
fauxdoc/emitter.py
fauxdoc/group.py
fauxdoc/mathtools.py
fauxdoc/mixins.py
fauxdoc/profile.py
fauxdoc/py.typed
fauxdoc/typing.py
fauxdoc/warn.py
fauxdoc/emitters/__init__.py
fauxdoc/emitters/choice.py
fauxdoc/emitters/fixed.py
fauxdoc/emitters/fromfields.py
fauxdoc/emitters/text.py
fauxdoc/emitters/wrappers.py
fauxdoc-1.1.0.dist-info/LICENSE
fauxdoc-1.1.0.dist-info/METADATA
fauxdoc-1.1.0.dist-info/WHEEL
fauxdoc-1.1.0.dist-info/top_level.txt
fauxdoc-1.1.0.dist-info/RECORD
