Metadata-Version: 2.1
Name: fauxdoc
Version: 1.1.0
Summary: Python package for generating fake (faux) record or document (doc) data conforming to bespoke requirements.
Author-email: Jason Thomale <jason.thomale@unt.edu>
Project-URL: Homepage, https://github.com/unt-libraries/fauxdoc
Project-URL: Repository, https://github.com/unt-libraries/fauxdoc
Project-URL: Changelog, https://github.com/unt-libraries/fauxdoc/blob/main/CHANGELOG.md
Keywords: data,fake,mock,faux,Solr,databases,models,fixtures,faker,testing,benchmarking,records,documents
Classifier: Development Status :: 5 - Production/Stable
Classifier: Intended Audience :: Developers
Classifier: License :: OSI Approved :: BSD License
Classifier: Programming Language :: Python
Classifier: Programming Language :: Python :: 3
Classifier: Programming Language :: Python :: 3 :: Only
Classifier: Programming Language :: Python :: 3.7
Classifier: Programming Language :: Python :: 3.8
Classifier: Programming Language :: Python :: 3.9
Classifier: Programming Language :: Python :: 3.10
Classifier: Programming Language :: Python :: 3.11
Classifier: Topic :: Software Development
Classifier: Topic :: Software Development :: Testing
Classifier: Topic :: Software Development :: Testing :: Mocking
Requires-Python: >=3.7
License-File: LICENSE
Requires-Dist: typing-extensions (>=3.6.5) ; python_version == "3.7"
Requires-Dist: importlib-metadata (>=2.0.0) ; python_version == "3.7"
Provides-Extra: dev
Requires-Dist: pytest (>=3.8.0) ; (python_version < "3.10") and extra == 'dev'
Requires-Dist: pytest (>=6.2.4) ; (python_version >= "3.10") and extra == 'dev'
